mudmaker/__init__.py
mudmaker/account_store.py
mudmaker/attributes.py
mudmaker/base.py
mudmaker/directions.py
mudmaker/exc.py
mudmaker/exits.py
mudmaker/game.py
mudmaker/main.py
mudmaker/menus.py
mudmaker/objects.py
mudmaker/parsers.py
mudmaker/rooms.py
mudmaker/socials.py
mudmaker/sources.py
mudmaker/tasks.py
mudmaker/util.py
mudmaker/websockets.py
mudmaker/zones.py
mudmaker/ext/admin_parser.py
mudmaker/ext/builder_parser.py
mudmaker-1.0.1.dist-info/AUTHORS
mudmaker-1.0.1.dist-info/LICENSE
mudmaker-1.0.1.dist-info/METADATA
mudmaker-1.0.1.dist-info/WHEEL
mudmaker-1.0.1.dist-info/entry_points.txt
mudmaker-1.0.1.dist-info/pbr.json
mudmaker-1.0.1.dist-info/top_level.txt
mudmaker-1.0.1.dist-info/RECORD
